conftext/__init__.py
conftext/conf_ini.py
conftext/conftext.py
conftext-0.0.12.dist-info/LICENSE
conftext-0.0.12.dist-info/METADATA
conftext-0.0.12.dist-info/WHEEL
conftext-0.0.12.dist-info/entry_points.txt
conftext-0.0.12.dist-info/top_level.txt
conftext-0.0.12.dist-info/RECORD
