Metadata-Version: 2.1
Name: conftext
Version: 0.0.12
Summary: conftext - helper for managing configuration contexts
Home-page: https://gitlab.dev.beat.no/backend/conftext
Author: Øystein S. Haaland
Author-email: oystein@beat.no
License-File: LICENSE
Requires-Dist: invoke
Requires-Dist: pydantic
Requires-Dist: importlib-metadata ; python_version < "3.8"
Provides-Extra: dev
Requires-Dist: twine ; extra == 'dev'
Requires-Dist: py ; extra == 'dev'
Requires-Dist: pytest ; extra == 'dev'
Requires-Dist: pytest-regtest ; extra == 'dev'
